{
  "id": "TB 1.7.1.7",
  "classification": {
    "prasna": "1",
    "prapaataka": "7",
    "anuvaka": "1",
    "panchasat": "7"
  },
  "header": "TB 1.7.1.7",
  "anuvaka_header": "1.7.1     अनुवाकं   1 - शुनासीरीयेन्द्रतुरीयपञ्चावत्तीयापामार्गहोमाः",
  "samhita": "न दिवा॒ न नक्त॒मिति॑ । स ए॒तम॒पां फेन॑मसिञ्चत् । न वा ए॒ष शुष्को॒ नार्द्रो व्यु॑ष्टा ऽऽसीत् । अनु॑दितः॒ सूर्यः॑ । न वा ए॒तद्-दिवा॒ न नक्त᳚म् । तस्यै॒तस्मि॑न् ॅलो॒के । अ॒पां फेने॑न॒ शिर॒ उद॑वर्तयत् । तदे॑न॒मन्व॑वर्तत । मित्र॑द्रु॒गिति॑",
  "korvai": "(य॒च्छ॒ति॒ - वरु॑णं॒ तृती॑यं॒ - ॅविजि॑त्या - असृजत॒ - समृ॑द्ध्यै - हनो॒ - मित्र॑द्रु॒गिति॑ - हन्ति॒ - स्तृत्यै॒ त्रीणि॑ च)"
}