{
  "id": "TB 3.10.8.5",
  "classification": {
    "prasna": "3",
    "prapaataka": "10",
    "anuvaka": "8",
    "panchasat": "5"
  },
  "header": "TB 3.10.8.5",
  "anuvaka_header": "3.10.8    अनुवाकं   8 -अनुवाकेषु नवसु लेखासु नाभ्यां चेष्टकोपधानं स्वयमातृण्णोपधानं चोच्यते",
  "samhita": "प्रा॒णो हृद॑ये । हृद॑यं॒ मयि॑ । अ॒हम॒मृते᳚ । अ॒मृतं॒ ब्रह्म॑णि ।सूर्यो॑ मे॒ चक्षु॑षि श्रि॒तः । चक्षु॒र्॒. हृद॑ये । हृद॑यं॒ मयि॑ । अ॒हम॒मृते᳚ । अ॒मृतं॒ ब्रह्म॑णि । च॒न्द्रमा॑ मे॒ मन॑सि श्रि॒तः",
  "korvai": "(स॒ह॒स्रिण॑ - मिहि॒ - श्रोत्रासा॒वेहि॑ - प्रा॒णे श्रि॒तो - मन॑सि श्रि॒तो - रेत॑सि श्रि॒ता - लोम॑सु श्रि॒ता - मू॒र्द्ध्नि श्रि॒त - आ॒त्मनि॑ श्रि॒तो᳚ - +ऽष्टौ च॑)"
}