{
  "id": "TB 2.1.6.3",
  "classification": {
    "prasna": "2",
    "prapaataka": "1",
    "anuvaka": "6",
    "panchasat": "3"
  },
  "header": "TB 2.1.6.3",
  "anuvaka_header": "2.1.6     अनुवाकं   6 - अभ्युद्द्रवणं, होमाभावप्रतीकारश्च",
  "samhita": "त॒नुवा॑ अ॒हमिति॑ वा॒युः । चक्षु॑षो॒ऽहमित्या॑दि॒त्यः । य ए॒व प्रा॒णाना॒महौ॑षीत् । तस्य॑ हु॒ताद॑ज॒नीति॑ । अ॒ग्नेर्. हु॒ताद॑ज॒नीति॑ । तद॑ग्निहो॒त्रस्या᳚-ग्निहोत्र॒त्वम् । गौर्वा अ॑ग्निहो॒त्रम् । य ए॒वं ॅवेद॒ गौर॑ग्निहो॒त्रमिति॑ । प्रा॒णा॒पा॒नाभ्या॑-मे॒वाग्निꣳ सम॑र्द्धयति । अव्य॑र्द्धुकः प्राणापा॒नाभ्यां᳚ भवति",
  "korvai": "(त॒नुवै॑ वा॒यु - र॒ग्निर् - भ॑व॒ - त्यवि॑त्त्वा - भव॒त्येकं॑ च)"
}