{
  "id": "TB 3.8.8.2",
  "classification": {
    "prasna": "3",
    "prapaataka": "8",
    "anuvaka": "8",
    "panchasat": "2"
  },
  "header": "TB 3.8.8.2",
  "anuvaka_header": "3.8.8     अनुवाकं   8 -अश्वचरितानामश्वरूपाणां च होमाः",
  "samhita": "तदा॑हुः । अना॑हुतयो॒ वा अ॑श्वचरि॒तानि॑ । नैता हो॑त॒व्या॑ इति॑ । अथो॒ खल्वा॑हुः । हो॒त॒व्या॑ ए॒व । अत्र॒ वावैवं ॅवि॒द्वान॑श्वमे॒धꣳ सꣳस्था॑पयति । यद॑श्व-चरि॒तानि॑ जु॒होति॑ । तस्मा᳚-द्धोत॒व्या॑ इति॑ ॥ ब॒हि॒र्द्धा वा ए॑नमे॒तदा॒यत॑नाद्-दधाति । भ्रातृ॑व्यमस्मै जनयति",
  "korvai": "(अ॒द्र्ध॒य॒ति॒ - ज॒न॒य॒ति॒ - खल्वा॑हु॒र् - जग॑ती॒ त्रीणि॑ च)"
}