{
  "id": "TB 2.7.1.3",
  "classification": {
    "prasna": "2",
    "prapaataka": "7",
    "anuvaka": "1",
    "panchasat": "3"
  },
  "header": "TB 2.7.1.3",
  "anuvaka_header": "2.7.1     अनुवाकं   1 - बृहस्पतिसवः",
  "samhita": "पु॒रो॒धामे॒व ग॑च्छति ॥ तस्य॑ प्रातस्सव॒ने स॒न्नेषु॑ नाराशꣳ॒॒सेषु॑ । एका॑दश॒ दक्षि॑णा नीयन्ते । एका॑दश॒ माद्ध्य॑दिंने॒ सव॑ने स॒न्नेषु॑ नाराशꣳ॒॒सेषु॑ । एका॑दश तृतीयसव॒ने स॒न्नेषु॑ नाराशꣳ॒॒सेषु॑ । त्रय॑स्त्रिꣳश॒थ्-संप॑द्यन्ते । त्रय॑स्त्रिꣳश॒द् वै दे॒वताः᳚ । दे॒वता॑ ए॒वाव॑रुन्धे ॥ अश्व॑श्चतुस्त्रिꣳ॒॒शः । प्रा॒जा॒प॒त्यो वा अश्वः॑",
  "korvai": "(होता॑ भवति - यजेत॒ - वा अश्वो॑ - दधाति)"
}