{
  "id": "TA 8.2.2",
  "classification": {
    "prapaataka": "8",
    "anuvaka": "2",
    "panchasat": "2"
  },
  "header": "TA 8.2.2",
  "samhita": " दे॒वता॑यै वषट्का॒राय॑ । यच्च॑तुर्गृही॒तम् जु॒होति॑ ।  छन्दाꣳ॑स्ये॒व तत् प्री॑णाति । तान्य॑स्य प्री॒तानि॑ दे॒वेभ्यो॑ ह॒व्यं ॅव॑हन्ति । ब्र॒ह्म॒वा॒दिनो॑ वदन्ति । हो॒त॒व्य॑म् दीक्षि॒तस्य॑ गृ॒हा(3) इ न हो॑त॒व्या(3) मिति॑ । ह॒विर्वै दी᳚क्षि॒तः । यज्जु॑हु॒यात् । ह॒विष्कृ॑तं॒ ॅयज॑मानम॒ग्नौ प्रद॑द्ध्यात् ।  यन्न जु॑हु॒यात् ",
  "korvai": "(या॒जा॑यै॒ - न जु॑हु॒या - दवि॑श॒द् - वेणः॒ - शान्त्यै॑ - प॒ङ्क्तिरा॑धस॒मित्या॑ह - हरति - दिहन्ति - प॒राक्र॑म॒ - तावि॑शत् - प्र॒जाय॑मानानाꣳ - सृजति - श॒न्त्वाया॒ ष्टौ च॑)"
}