{
  "id": "TA 8.2.4",
  "classification": {
    "prapaataka": "8",
    "anuvaka": "2",
    "panchasat": "4"
  },
  "header": "TA 8.2.4",
  "samhita": " स ख॑दि॒रो॑ऽभवत् । यः प॒शून् । सो॑ऽजाम् । यत्खा॑दि॒र्यभ्रि॒र् भव॑ति । छन्द॑सामे॒व रसे॑न य॒ज्ञ्स्य॒ शिरः॒ सम्भ॑रति । यदौदु॑म्बरी ।  ऊर्ग्वा उ॑दु॒म्बरः॑ । ऊ॒र्जैव य॒ज्ञ्स्य॒ शिरः॒ सम्भ॑रति । यद्-वै॑ण॒वी । तेजो॒ वै वेणुः॑ ",
  "korvai": "(या॒जा॑यै॒ - न जु॑हु॒या - दवि॑श॒द् - वेणः॒ - शान्त्यै॑ - प॒ङ्क्तिरा॑धस॒मित्या॑ह - हरति - दिहन्ति - प॒राक्र॑म॒ - तावि॑शत् - प्र॒जाय॑मानानाꣳ - सृजति - श॒न्त्वाया॒ ष्टौ च॑)"
}