{
  "id": "TB 3.3.6.8",
  "classification": {
    "prasna": "3",
    "prapaataka": "3",
    "anuvaka": "6",
    "panchasat": "8"
  },
  "header": "TB 3.3.6.8",
  "anuvaka_header": "3.3.6     अनुवाकं   6 - स्त्रुख्सादनम्",
  "samhita": "ब॒र्॒.॒हिः स्तृ॑णाति । प्र॒जा वै ब॒र्.॒हिः । पृ॒थि॒वी वेदिः॑ । प्र॒जा ए॒व पृ॑थि॒व्यां प्रति॑ष्ठापयति ॥ अन॑तिदृश्नꣳ स्तृणाति । प्र॒जयै॒वैनं॑ प॒शुभि॒रन॑तिदृश्नं करोति । धा॒रय॑न् प्रस्त॒रं प॑रि॒धीन् परि॑ दधाति । यज॑मानो॒ वै प्र॑स्त॒रः । यज॑मान ए॒व तथ् स्व॒यं प॑रि॒धीन् परि॑ दधाति ॥ ग॒न्ध॒र्वो॑ऽसि वि॒श्वाव॑सु॒रित्या॑ह",
  "korvai": "(स्थेत्या॑ह - पृथि॒वी वेदि॒र् - यन्ति॑ - क्रि॒यते॒ - विष्णु॑र् - वी॒र्य॑संमितं - करो - त्याह - पाति॒ - नाम्नेत्या॑ह - लो॒के सा॑दयति॒ षट्च॑)"
}