{
  "id": "TB 1.1.10.3",
  "classification": {
    "prasna": "1",
    "prapaataka": "1",
    "anuvaka": "10",
    "panchasat": "3"
  },
  "header": "TB 1.1.10.3",
  "anuvaka_header": "1.1.10    अनुवाकं   10 - पञ्चाग्न्याधानम्",
  "samhita": "सा च॑तु॒र्थ-मुद॑क्रामत् । तत् प्र॒जाप॑तिः॒ पर्य॑गृह्णात् । सप्र॑थ स॒भां मे॑ गोपा॒येति॑ । सा प॑ञ्च॒म-मुद॑क्रामत् । तत् प्र॒जाप॑तिः॒ पर्य॑गृह्णात् । अहे॑ बुद्ध्निय॒ मन्त्रं॑ मे गोपा॒येति॑ । अ॒ग्नीन् वाव सा तान् व्य॑क्रमत । तान् प्र॒जाप॑तिः॒ पर्य॑गृह्णात् । अथो॑ प॒ङ्क्तिमे॒व ॥ प॒ङ्क्तिर्वा ए॒षा ब्रा᳚ह्म॒णे प्रवि॑ष्टा",
  "korvai": "(ए॒षा - प॒शून्मे॑ गोपा॒येति॒ - प्रवि॑ष्टा - \nप॒शून्मे॑ गोपा॒येत्या॑ह॒ - जुह्व॑ति - तिष्ठते स॒प्त च॑)"
}