{
  "id": "TA 6.67.4",
  "classification": {
    "prapaataka": "6",
    "anuvaka": "67",
    "panchasat": "4"
  },
  "header": "TA 6.67.4",
  "samhita": " दे॒वेभ्यः॒ स्वाहा᳚ । पि॒तृभ्यः॑ स्व॒धाऽस्तु॑ । भू॒तेभ्यो॒ नमः॑ । म॒नु॒ष्ये᳚भ्यो॒ हन्ता᳚ । प्र॒जाप॑तये॒ स्वाहा᳚ । प॒र॒मे॒ष्ठिने॒ स्वाहा᳚ ॥  यथा कू॑पः श॒तधा॑रः स॒हस्र॑धारो॒ अक्षि॑तः ।  ए॒वा मे॑ अस्तु धा॒न्यꣳ स॒हस्र॑धार॒-मक्षि॑तं । धन॑धान्यै॒ स्वाहा᳚ ॥  ये भू॒ताः प्र॒चर॑न्ति॒ दिवा॒नक्तं॒ बलि॑-मि॒च्छन्तो॑ वि॒तुद॑स्य॒ प्रेष्याः᳚ ( ) । तेभ्यो॑ ब॒लिं पु॑ष्टि॒कामो॑ हरामि॒ मयि॒ पुष्टिं॒ पुष्टि॑पतिर् दधातु॒ स्वाहा᳚ ।",
  "korvai": "(ओ॒ष॒धि॒व॒न॒स्प॒तिभ्यः॒ स्वाहा॒ - ऽन्तरि॑क्षाय॒ स्वाहा॒ - नमो॑ रु॒द्राय॑ पशु॒पत॑ये॒ स्वाहा॑ - वि॒तुद॑स्य॒ प्रेष्या॒ एकं॑ च)"
}