{
  "id": "TB 3.7.5.12",
  "classification": {
    "prasna": "3",
    "prapaataka": "7",
    "anuvaka": "5",
    "panchasat": "12"
  },
  "header": "TB 3.7.5.12",
  "anuvaka_header": "3.7.5     अनुवाकं   5 -ऐष्टिकयाजमानमन्त्राः",
  "samhita": "ऊ॒र्जो भा॒गꣳ श॑तक्रतू । ए॒तद्वां॒ तेन॑ प्रीणानि । तेन॑ तृप्यतमꣳहहौ ॥ अ॒हं दे॒वानाꣳ॑ सु॒कृता॑मस्मि लो॒के । ममे॒दमि॒ष्टं न मिथु॑ र्भवाति । अ॒हं ना॑रि॒ष्ठा-वनु॑यजामि वि॒द्वान् । यदा᳚भ्या॒-मिन्द्रो॒ अद॑धा-द्भाग॒धेयं᳚ ॥ अदा॑रसृद्भवत देव सोम । अ॒स्मिन्. य॒ज्ञे म॑रुतो मृडता नः । मा नो॑ विदद॒भि भा॒मो अश॑स्तिः",
  "korvai": "(अ॒भीत्व॑र्यै - करोमि - क्रमीत् - पि॒ता - ऽऽत्मन॑ - एक॒तोमु॑खां - मे॒ दिशो - ऽध्य॑क्षेभ्यो - ह॒विर् - गा॑र्.हपत्या - कल्पय॒ - न्नश॑स्तिः॒ - सा नो॑ दोहताꣳ सु॒वीर्यꣳ॑ स॒प्त च॑)"
}