{
  "id": "TS 4.3.11.4",
  "classification": {
    "kanda": "4",
    "prasna": "3",
    "anuvaka": "11",
    "panchasat": "4"
  },
  "header": "TS 4.3.11.4",
  "panchasatInfo": " 24",
  "padaCount": 50,
  "samhita": "मस्य सुम॒तौ यथा॑ यू॒यम॒न्या वो॑ अ॒न्यामति॒ मा प्र यु॑क्त ॥ अभू॒न्मम॑ सुम॒तौ वि॒श्ववे॑दा॒ आष्ट॑ प्रति॒ष्ठामवि॑द॒द्धि गा॒धं । भू॒यास॑मस्य सुम॒तौ यथा॑ यू॒यम॒न्या वो॑ अ॒न्यामति॒ मा प्रयु॑क्त ॥ पञ्च॒ व्यु॑ष्टी॒रनु॒ पञ्च॒ दोहा॒ गां पञ्च॑नाम्नीमृ॒तवोऽनु॒ पञ्च॑ । पञ्च॒ दिशः॑ पञ्चद॒शेन॑ क्लृ॒प्ताः स॑मा॒नमू᳚र्द्ध्नीर॒भि लो॒कमेकं᳚ ॥",
  "pada": "अ॒स्य॒ । सु॒म॒ताविति॑ सु - म॒तौ । यथा᳚ । यू॒यम् । अ॒न्या । वः॒ । अ॒न्याम् । अतीति॑ । मा । प्रेति॑ । यु॒क्त॒ ।  । अभू᳚त् । मम॑ । सु॒म॒ताविति॑ सु - म॒तौ । वि॒श्ववे॑दा॒ इति॑ वि॒श्व - वे॒दाः॒ । आष्ट॑ । प्र॒ति॒ष्ठामिति॑ प्रति - स्थाम् । अवि॑दत् । हि । गा॒धम् ।  । भू॒यास᳚म् । अ॒स्य॒ । सु॒म॒ताविति॑ सु - म॒तौ । यथा᳚ । यू॒यम् । अ॒न्या । वः॒ । अ॒न्याम् । अतीति॑ । मा । प्रेति॑ । यु॒क्त॒ ।  । पञ्च॑ । व्यु॑ष्टी॒रिति॒ वि - उ॒ष्टीः॒ । अन्विति॑ । पञ्च॑ । दोहाः᳚ । गाम् । पञ्च॑नाम्नी॒मिति॒ पञ्च॑ - ना॒म्नी॒म् । ऋ॒तवः॑ । अन्विति॑ । पञ्च॑ ।  । पञ्च॑ । दिशः॑ । प॒ञ्च॒द॒शेनेति॑ पञ्च - द॒शेन॑ । क्लृ॒प्ताः । स॒मा॒नमू᳚र्द्ध्नी॒रिति॑ समा॒न - मू॒र्द्ध्नीः॒ । अ॒भीति॑ । लो॒कम् । एक᳚म् ।  । ",
  "attribute": {
    "rishi": "अज्ञात",
    "devata": "अज्ञात",
    "chandas": "अज्ञात"
  }
}