{
  "id": "TB 1.6.7.4",
  "classification": {
    "prasna": "1",
    "prapaataka": "6",
    "anuvaka": "7",
    "panchasat": "4"
  },
  "header": "TB 1.6.7.4",
  "anuvaka_header": "1.6.7     अनुवाकं   7 - तच्छेषः",
  "samhita": "भा॒ग॒धेये॑ने॒वैनꣳ॒॒ सम॑र्द्धयति । ऋ॒ष॒भमाह्व॑यति । व॒ष॒ट्का॒र ए॒वास्य॒ सः । अथो॑ इन्द्रि॒यमे॒व तद्-वी॒र्यं॑ ॅयज॑मानो॒ भ्रातृ॑व्यस्य वृङ्क्ते । इन्द्रो॑ वृ॒त्रꣳ ह॒त्वा । परां᳚ परा॒वत॑-मगच्छत् । अपा॑राध॒मिति॒ मन्य॑मानः । सो᳚ऽब्रवीत् । क इ॒दं ॅवे॑दिष्य॒तीति॑ । ते᳚ऽब्रुवन् म॒रुतो॒ वरं॑ ॅवृणामहै",
  "korvai": "(ऋ॒द्ध्य॒ते॒ऽ-भ्य॑ञ्जते-जुहोति-वृणामहै-भवत्य॒- +ष्टौ च॑)"
}