{
  "id": "TB 2.7.2.1",
  "classification": {
    "prasna": "2",
    "prapaataka": "7",
    "anuvaka": "2",
    "panchasat": "1"
  },
  "header": "TB 2.7.2.1",
  "anuvaka_header": "2.7.2      अनुवाकं   2 - वैश्यसवः",
  "samhita": "यदा᳚ग्ने॒यो भव॑ति । अ॒ग्निमु॑खा॒ ह्यृद्धिः॑ ॥ अथ॒ यत् पौ॒ष्णः । पुष्टि॒र्वै पू॒षा । पुष्टि॒र्-वैश्य॑स्य । पुष्टि॑मे॒वाव॑रुन्धे ॥ प्र॒स॒वाय॑ सावि॒त्रः ॥ अथ॒ यत् त्वा॒ष्ट्रः । त्वष्टा॒ हि रू॒पाणि॑ विक॒रोति॑ ॥ नि॒र्व॒रु॒ण॒त्वाय॑ वारु॒णः",
  "korvai": "(वा॒रु॒णो - विड्वै म॒रुतो॒ऽष्टौ च॑)"
}