{
  "id": "TB 2.3.10.3",
  "classification": {
    "prasna": "2",
    "prapaataka": "3",
    "anuvaka": "10",
    "panchasat": "3"
  },
  "header": "TB 2.3.10.3",
  "anuvaka_header": "2.3.10    अनुवाकं   10 - दशहोतृमन्त्राणां काम्यप्रयोगः",
  "samhita": "आऽस्यार्द्धं ॅव॑व्राज । ताꣳ हो॒दीक्ष्यो॑वाच । उप॒ माऽऽव॑र्त॒स्वेति॑ । तꣳ हो॑वाच । भोगं॒ तु म॒ आच॑क्ष्व । ए॒तन् म॒ आच॑क्ष्व । यत्ते॑ पा॒णाविति॑ । तस्या॑ उ॒ ह त्रीन्. वेदा॒न् प्रद॑दौ । तस्मा॒दु ह॒ स्त्रियो॒ भोग॒मैव हा॑रयन्ते ॥ स यः का॒मये॑त प्रि॒यः स्या॒मिति॑",
  "korvai": "(अ॒या॒ - न्य॒ल॒ङ्कृत्य॑ - स्या॒मिति॑ - भवति)"
}