{
  "id": "TS 7.2.16.1",
  "classification": {
    "kanda": "7",
    "prasna": "2",
    "anuvaka": "16",
    "panchasat": "1"
  },
  "header": "TS 7.2.16.1",
  "panchasatInfo": " 46",
  "padaCount": 14,
  "samhita": "प॒ञ्चभ्यः॒ स्वाहा॑ द॒शभ्यः॒ स्वाहा॑ पञ्चद॒शभ्यः॒ स्वाहा॑ विꣳश॒त्यै स्वाहा॒ पञ्च॑नवत्यै॒ स्वाहा॑ श॒ताय॒ स्वाहा॒ सर्व॑स्मै॒ स्वाहा᳚ ॥",
  "pada": "प॒ञ्चभ्य॒ इति॑ प॒ञ्च - भ्यः॒ । स्वाहा᳚ । द॒शभ्य॒ इति॑ द॒श - भ्यः॒ । स्वाहा᳚ । प॒ञ्च॒द॒शभ्य॒ इति॑ पञ्चद॒श - भ्यः॒ । स्वाहा᳚ । विꣳ॒॒श॒त्यै । स्वाहा᳚ । पञ्च॑नवत्या॒ इति॒ पञ्च॑ - न॒व॒त्यै॒ । स्वाहा᳚ । श॒ताय॑ । स्वाहा᳚ । सर्व॑स्मै । स्वाहा᳚ ।  । ",
  "attribute": {
    "rishi": "अज्ञात",
    "devata": "अज्ञात",
    "chandas": "अज्ञात"
  }
}