{
  "id": "TB 2.6.11.8",
  "classification": {
    "prasna": "2",
    "prapaataka": "6",
    "anuvaka": "11",
    "panchasat": "8"
  },
  "header": "TB 2.6.11.8",
  "anuvaka_header": "2.6.11    अनुवाकं   11 - पशुत्रये प्रय जार्था मैत्रावरुणप्रैषाः",
  "samhita": "श्रि॒या न मास॑रम् । पयः॒ सोमः॑ परि॒स्रुता॑ घृ॒तं मधु॑ । वि॒यन्त्वाज्य॑स्य॒ होत॒र्यज॑ ॥ होता॑ यक्ष॒द्-वन॒स्पति᳚म् । श॒मि॒तारꣳ॑ श॒तक्र॑तुम् । भी॒मं न म॒न्युꣳ राजा॑नं ॅव्या॒घ्रं नम॑सा॒ऽश्विना॒ भामं᳚ । सर॑स्वती भि॒षक् । इन्द्रा॑य दुह इन्द्रि॒यम् । पयः॒ सोमः॑ परि॒स्रुता॑ घृ॒तं मधु॑ । वि॒यन्त्वाज्य॑स्य॒ होत॒र्यज॑ ।",
  "korvai": "(वी॒र्यं - ॅवि॒यन्त्वाज्य॑स्य॒ होत॒र्यज॒ - नास॑त्या॒ - सर॑स्वती॒ - मधु॑ - हिर॒ण्ययं॑ - भेष॒जं - ॅवि॒यन्त्वाज्य॑स्य॒ होत॒र्यजा᳚ - ज्य॒पा - न॒मृताः॒ पञ्च॑ च)"
}