{
  "id": "TB 1.1.9.3",
  "classification": {
    "prasna": "1",
    "prapaataka": "1",
    "anuvaka": "9",
    "panchasat": "3"
  },
  "header": "TB 1.1.9.3",
  "anuvaka_header": "1.1.9     अनुवाकं   9 - ब्रह्मौदनम्",
  "samhita": "तस्या॑ उ॒च्छेष॑ण-मददुः । तत् प्राश्ञा᳚त् । सा रेतो॑ऽधत्त । तस्या॒ इन्द्र॑श्च॒ विव॑स्वाꣳश्चा-जायेताम् । ब्र॒ह्मौ॒द॒नं प॑चति । रेत॑ ए॒व तद्-द॑धाति ॥ प्राश्ञ॑न्ति ब्राह्म॒णा ओ॑द॒नम् ॥ यदाज्य॑-मु॒च्छिष्य॑ते । तेन॑ स॒मिधो॒ऽभ्यज्याद॑धाति । उ॒च्छेष॑णा॒द्वा अदि॑ती॒ रेतो॑ऽधत्त",
  "korvai": "(द्वि॒तीय॑मपचच् - चतु॒र्थम॑पच॒ - ददि॑ती॒ रेतो॑ऽधत्त॒ - संमि॑ता - \nघृ॒तव॑तीभि॒राद॑धाति - राज॒न्यः॑ स्वस्य॒ छन्द॑सः प्रत्ययन॒स्त्वा - ये॑याद् - गच्छति - मन्थति॒ - रात्र॑य श्च॒त्वारि॑ च)"
}