{
  "id": "TS 7.4.5.1",
  "classification": {
    "kanda": "7",
    "prasna": "4",
    "anuvaka": "5",
    "panchasat": "1"
  },
  "header": "TS 7.4.5.1",
  "panchasatInfo": " 18",
  "padaCount": 50,
  "samhita": "द्वे वाव दे॑वस॒त्रे द्वा॑दशा॒हश्चै॒व त्र॑यस्त्रिꣳशद॒हश्च॒ य ए॒वं ॅवि॒द्वाꣳस॑स्त्रयस्त्रिꣳशद॒हमास॑ते सा॒क्षादे॒व दे॒वता॑ अ॒भ्यारो॑हन्ति॒ यथा॒ खलु॒ वै श्रेया॑न॒भ्यारू॑ढः का॒मय॑ते॒ तथा॑ करोति॒ यद्य॑व॒विद्ध्य॑ति॒ पापी॑यान् भवति॒ यदि॒ नाव॒विद्ध्य॑ति स॒दृङ् य ए॒वं ॅवि॒द्वाꣳस॑स्त्रयस्त्रिꣳ- शद॒हमास॑ते॒ वि पा॒प्मना॒ भ्रातृ॑व्ये॒णाऽऽ* व॑र्तन्ते ऽह॒र्भाजो॒ वा ए॒ता दे॒वा अग्र॒ आऽह॑र॒ - [  ]",
  "pada": "द्वे इति॑ । वाव । दे॒व॒स॒त्रे इति॑ देव - स॒त्रे । द्वा॒द॒शा॒ह इति॑ द्वादश-अ॒हः । च॒ । ए॒व । त्र॒य॒स्त्रिꣳ॒॒श॒द॒ह इति॑ त्रयस्त्रिꣳशत्-अ॒हः । च॒ । ये । ए॒वम् । वि॒द्वाꣳसः॑ । त्र॒य॒स्त्रिꣳ॒॒श॒द॒हमिति॑ त्रयस्त्रिꣳशत्-अ॒हम् । आस॑ते । सा॒क्षादिति॑ स - अ॒क्षात् । ए॒व । दे॒वताः᳚ । अ॒भ्यारो॑ह॒न्तीत्य॑भि - आरो॑हन्ति । यथा᳚ । खलु॑ । वै । श्रेयान्॑ । अ॒भ्यारू॑ढ॒ इत्य॑भि - आरू॑ढः । का॒मय॑ते । तथा᳚ । क॒रो॒ति॒ । यदि॑ । अ॒व॒विद्ध्य॒तीत्य॑व - विद्ध्य॑ति । पापी॑यान् । भ॒व॒ति॒ । यदि॑ । न । अ॒व॒विद्ध्य॒तीत्य॑व - विद्ध्य॑ति । स॒दृङ्ङिति॑ स - दृङ् । ये । ए॒वम् । वि॒द्वाꣳसः॑ । त्र॒य॒स्त्रिꣳ॒॒श॒द॒हमिति॑ त्रयस्त्रिꣳशत् - अ॒हम् । आस॑ते । वीति॑ । पा॒प्मना᳚ । भ्रातृ॑व्येण । एति॑ । व॒र्त॒न्ते॒ । अ॒ह॒र्भाज॒ इत्य॑हः - भाजः॑ । वै । ए॒ताः । दे॒वाः । अग्रे᳚ । एति॑ । अ॒ह॒र॒न्न् । ",
  "attribute": {
    "rishi": "अज्ञात",
    "devata": "अज्ञात",
    "chandas": "अज्ञात"
  }
}