{
  "id": "TA 1.22.6",
  "classification": {
    "prapaataka": "1",
    "anuvaka": "22",
    "panchasat": "6"
  },
  "header": "TA 1.22.6",
  "samhita": " यो॑ऽपामा॒यत॑नं॒ ॅवेद॑ । आ॒यत॑नवान् भवति । प॒र्जन्यो॒ वा अ॒पामा॒यत॑नं । आ॒यत॑नवान् भवति ।  य: प॒र्जन्य॑-स्या॒यत॑नं॒ ॅवेद॑ ।  आ॒यत॑नवान् भवति । आपो॒ वै प॒र्जन्य॑-स्या॒यत॑नं ।  आ॒यत॑नवान् भवति । य ए॒वं ॅवेद॑ ॥ यो॑ऽपामा॒यत॑नं॒ ॅवेद॑ ।",
  "korvai": "(वेद॑ - भव - त्या॒यत॑नं - भवति॒ - वेद॒ - वेद॑ - तिष्ठति - गुल्फद॒घ्नं - चा॑तुर्मा॒स्ये - ष्व॒मुमा॑दि॒त्यं प्र॒त्यक्षे॑ण॒ कम॒ग्निं चि॑नुत - उपानुवा॒क्य॑मा॒शुम॒ग्निं चि॑न्वा॒नो - मि॑थू॒या मि॑थुन॒वान् भ॑व॒त्येकं॑ च)"
}