{
  "id": "TB 1.1.2.5",
  "classification": {
    "prasna": "1",
    "prapaataka": "1",
    "anuvaka": "2",
    "panchasat": "5"
  },
  "header": "TB 1.1.2.5",
  "anuvaka_header": "1.1.2     अनुवाकं   2 - अथाग्न्याधानप्रकरणं, तत्र कालविशेषविधिः",
  "samhita": "ते सु॑व॒र्गाय॑ लो॒काया॒ग्नि-म॑चिन्वत । पुरु॑ष॒ इष्ट॑का॒-मुपा॑दधा॒त्-पुरु॑ष॒ इष्ट॑काम् । स इन्द्रो᳚ ब्राह्म॒णो ब्रुवा॑ण॒ इष्ट॑का॒मुपा॑धत्त । ए॒षा मे॑ चि॒त्रा नामेति॑ । ते सु॑व॒र्गं ॅलो॒कमाप्रारो॑हन्न् । स इन्द्र॒ इष्ट॑का॒मावृ॑हत् । तेऽवा॑कीर्यन्त । ये॑ऽवाकी᳚र्यन्त । त ऊर्णा॒वभ॑योऽभवन्न् । द्वावुद॑पतताम्",
  "korvai": "(खल्वा॑ - धिथ्सन्त॒ - फल्गु॑न्योर॒ग्निमाद॑धीता - सन् - नपतता - मतू॒नां - ॅवैश्य॑स्य॒र्तु - रुत्त॑रे॒ फल्गु॑नी॒ षट् च॑)"
}