{
  "id": "TB 1.4.5.2",
  "classification": {
    "prasna": "1",
    "prapaataka": "4",
    "anuvaka": "5",
    "panchasat": "2"
  },
  "header": "TB 1.4.5.2",
  "anuvaka_header": "1.4.5      अनुवाकं   5 - सोमातिरेकप्रायश्चित्तम्",
  "samhita": "म॒रुत्व॑तीषु कुर्वन्ति । तेनै॒व माद्ध्य॑न्दिना॒थ्-सव॑ना॒न्नय॑न्ति ॥ होतु॑श्च म॒समनून्न॑यन्ते । होताऽनु॑शꣳसति । म॒द्ध्य॒त ए॒व य॒ज्ञ्ꣳ स॒माद॑धाति ॥ यस्य॒ माद्ध्य॑न्दिने॒ सव॑ने॒ सोमो॑ऽति॒रिच्य॑ते । आ॒दि॒त्यं तृ॑तीयसव॒नं का॒मय॑मानो॒-ऽभ्यति॑रिच्यते । गौ॒रि॒वी॒तꣳ साम॑ भवति । अति॑रिक्तं॒ ॅवै गौ॑रिवी॒तम् । अति॑रिक्तं॒ ॅयथ् सव॑नस्या-ति॒रिच्य॑ते",
  "korvai": "(य॒न्ति॒ - सव॑नस्याति॒रिच्य॑ते - शꣳसति - दाधारा॒ष्टौ च॑)"
}