{
  "id": "TS 5.5.4.3",
  "classification": {
    "kanda": "5",
    "prasna": "5",
    "anuvaka": "4",
    "panchasat": "3"
  },
  "header": "TS 5.5.4.3",
  "panchasatInfo": " 20",
  "padaCount": 50,
  "samhita": "ञ्च॒न प्र॒त्यव॑रोहे॒न्न हीमे कञ्च॒न प्र॑त्यव॒रोह॑त॒स्तदे॑नयोर्व्र॒तं ॅयो वा अप॑ शीर्.षाणम॒ग्निं चि॑नु॒तेऽप॑शीर्.षा॒ऽमुष्मि॑न् ॅलो॒के भ॑वति॒ यः सशी॑र्.षाणं चिनु॒ते सशी॑र्.षा॒ ऽमुष्मि॑न् ॅलो॒के भ॑वति॒ चित्तिं॑ जुहोमि॒ मन॑सा घृ॒तेन॒ यथा॑ दे॒वा इ॒हाऽऽ*गम॑न् वी॒तिहो᳚त्रा ऋता॒वृधः॑ समु॒द्रस्य॑ व॒युन॑स्य॒ पत्म॑न् जु॒होमि॑ वि॒श्वक॑र्मणे॒ विश्वाऽहाऽम॑र्त्यꣳ ह॒विरिति॑ स्वयमातृ॒ण्णामु॑प॒धाय॑ जुहोत्ये॒ - [  ]",
  "pada": "च॒न । प्र॒त्यव॑रोहे॒दिति॑ प्रति - अव॑रोहेत् । न । हि । इ॒मे इति॑ । कम् । च॒न । प्र॒त्य॒व॒रोह॑त॒ इति॑ प्रति - अ॒व॒रोह॑तः । तत् । ए॒न॒योः॒ । व्र॒तम् । यः । वै । अप॑शीर्.षाण॒मित्यप॑ - शी॒र्.॒षा॒ण॒म् । अ॒ग्निम् । चि॒नु॒ते । अप॑शी॒र्॒.षेत्यप॑ - शी॒र्.॒षा॒ । अ॒मुष्मिन्न्॑ । लो॒के । भ॒व॒ति॒ । यः । सशी॑र्.षाण॒मिति॒ स - शी॒र्.॒षा॒ण॒म् । चि॒नु॒ते । सशी॒र्॒.षेति॒ स - शी॒र्.॒षा॒ । अ॒मुष्मिन्न्॑ । लो॒के । भ॒व॒ति॒ । चित्ति᳚म् । जु॒हो॒मि॒ । मन॑सा । घृ॒तेन॑ । यथा᳚ । दे॒वाः । इ॒ह । आ॒गम॒न्नित्या᳚ - गमन्न्॑ । वी॒तिहो᳚त्रा॒ इति॑ वी॒ति - हो॒त्राः॒ । ऋ॒ता॒वृध॒ इत्यृ॑त - वृधः॑ । स॒मु॒द्रस्य॑ । व॒युन॑स्य । पत्मन्न्॑ । जु॒होमि॑ । वि॒श्वक॑र्मण॒ इति॑ वि॒श्व - क॒र्म॒णे॒ । विश्वा᳚ । अहा᳚ । अम॑र्त्यम् । ह॒विः । इति॑ । स्व॒य॒मा॒तृ॒ण्णामिति॑ स्वयं - आ॒तृ॒ण्णाम् । उ॒प॒धायेत्यु॑प - धाय॑ । जु॒हो॒ति॒ । ",
  "attribute": {
    "rishi": "अज्ञात",
    "devata": "अज्ञात",
    "chandas": "अज्ञात"
  }
}